arianeDevs/__init__.py
arianeDevs/responsedto.py
arianeDevs-0.1.6.dist-info/METADATA
arianeDevs-0.1.6.dist-info/WHEEL
arianeDevs-0.1.6.dist-info/top_level.txt
arianeDevs-0.1.6.dist-info/RECORD
